pypitesting/__init__.py
pypitesting/version.py
pypitesting/image_hashing/__init__.py
pypitesting/image_hashing/hashing.py
pypitesting-0.7.2.dist-info/LICENSE
pypitesting-0.7.2.dist-info/METADATA
pypitesting-0.7.2.dist-info/WHEEL
pypitesting-0.7.2.dist-info/top_level.txt
pypitesting-0.7.2.dist-info/RECORD
