Metadata-Version: 2.1
Name: pypitesting
Version: 0.7.2
Summary: test pypi
Home-page: https://github.com/ps-swarooppadala/pypitesting
Author: Swaroop Padala
Author-email: pswaroop1994@gmail.com
License: MIT
Keywords: pypi,hello world
Platform: UNKNOWN
Classifier: Development Status :: 2 - Pre-Alpha
Classifier: License :: OSI Approved :: MIT License
Classifier: Programming Language :: Python
Classifier: Programming Language :: Python :: 3
Classifier: Programming Language :: Python :: 3.4
Classifier: Programming Language :: Python :: 3.5
Classifier: Programming Language :: Python :: 3.6
Classifier: Programming Language :: Python :: 3.7
Requires-Dist: numpy
Requires-Dist: opencv-python
Requires-Dist: PyWavelets
Requires-Dist: pylint
Requires-Dist: scikit-learn
Requires-Dist: scipy
Requires-Dist: Pillow
